mltoolbox/__init__.py
mltoolbox/perceptron_classifier.py
mltoolbox/pocket_classifier.py
ml_toybox-0.0.2.dist-info/LICENSE
ml_toybox-0.0.2.dist-info/METADATA
ml_toybox-0.0.2.dist-info/WHEEL
ml_toybox-0.0.2.dist-info/entry_points.txt
ml_toybox-0.0.2.dist-info/top_level.txt
ml_toybox-0.0.2.dist-info/RECORD
